{"unit_type": "ESCALATOR", "performance_summary": {"one_day": {"break_days": [], "day_to_break_count": {}, "num_breaks": 0, "start_time": "2015-02-16T04:53:33.940000+00:00", "unit_id": "K03X03ESCALATOR", "broken_time_percentage": 0.0, "end_time": "2015-02-17T04:53:33.940000+00:00", "num_inspections": 0, "availability": 1.0}, "three_day": {"break_days": [], "day_to_break_count": {}, "num_breaks": 0, "start_time": "2015-02-14T04:53:33.940000+00:00", "unit_id": "K03X03ESCALATOR", "broken_time_percentage": 0.0, "end_time": "2015-02-17T04:53:33.940000+00:00", "num_inspections": 0, "availability": 1.0}, "thirty_day": {"break_days": [], "day_to_break_count": {}, "num_breaks": 0, "start_time": "2015-01-18T04:53:33.940000+00:00", "unit_id": "K03X03ESCALATOR", "broken_time_percentage": 0.0, "end_time": "2015-02-17T04:53:33.940000+00:00", "num_inspections": 0, "availability": 1.0}, "all_time": {"break_days": ["2013-06-07", "2013-06-13", "2013-06-14", "2013-06-27", "2013-06-28", "2013-07-12", "2013-07-15", "2013-10-02", "2013-10-07", "2013-10-08", "2013-10-10", "2013-10-26", "2013-11-02", "2013-11-10", "2013-11-14", "2013-11-25", "2014-01-29", "2014-02-08", "2014-03-20", "2014-04-13", "2014-04-15", "2014-05-04", "2014-05-07", "2014-05-15", "2014-05-16", "2014-05-22", "2014-05-23", "2014-05-25", "2014-07-07", "2014-08-12", "2014-08-26", "2014-08-31", "2014-09-01", "2014-10-15", "2014-11-06", "2014-11-07", "2014-11-08", "2014-11-09", "2014-11-13", "2014-11-29", "2014-12-15"], "day_to_break_count": {"2014-11-29": 1, "2014-05-25": 1, "2014-05-07": 1, "2014-04-15": 1, "2014-04-13": 2, "2014-05-16": 2, "2013-10-07": 1, "2014-05-22": 1, "2013-06-14": 1, "2013-06-13": 1, "2014-08-26": 1, "2013-10-26": 1, "2014-05-15": 1, "2013-10-08": 1, "2014-01-29": 1, "2013-11-02": 1, "2013-11-25": 1, "2014-11-13": 1, "2014-03-20": 1, "2014-07-07": 1, "2014-05-23": 1, "2013-10-02": 3, "2013-10-10": 1, "2013-06-28": 1, "2013-06-07": 1, "2014-08-12": 1, "2013-06-27": 2, "2014-12-15": 1, "2014-08-31": 1, "2014-05-04": 1, "2014-09-01": 1, "2013-07-15": 1, "2014-10-15": 1, "2013-11-10": 1, "2013-07-12": 1, "2013-11-14": 1, "2014-02-08": 1, "2014-11-06": 1}, "num_breaks": 43, "start_time": "2013-06-01T16:38:21.475000+00:00", "unit_id": "K03X03ESCALATOR", "broken_time_percentage": 0.010423375420748787, "end_time": "2015-02-17T04:53:33.940000+00:00", "num_inspections": 22, "availability": 0.9882546028520284}, "fourteen_day": {"break_days": [], "day_to_break_count": {}, "num_breaks": 0, "start_time": "2015-02-03T04:53:33.940000+00:00", "unit_id": "K03X03ESCALATOR", "broken_time_percentage": 0.0, "end_time": "2015-02-17T04:53:33.940000+00:00", "num_inspections": 0, "availability": 1.0}, "seven_day": {"break_days": [], "day_to_break_count": {}, "num_breaks": 0, "start_time": "2015-02-10T04:53:33.940000+00:00", "unit_id": "K03X03ESCALATOR", "broken_time_percentage": 0.0, "end_time": "2015-02-17T04:53:33.940000+00:00", "num_inspections": 0, "availability": 1.0}}, "station_code": "K03", "unit_id": "K03X03ESCALATOR", "esc_desc": "Escalator between street and mezzanine", "station_desc": "", "station_name": "VIRGINIA SQUARE-GMU", "key_statuses": {"lastInspectionStatus": {"symptom_description": "Preventive Maintenance Inspection", "symptom_category": "INSPECTION", "unit_id": "K03X03ESCALATOR", "end_time": "2014-11-12T09:09:25.091000+00:00", "update_type": "Off", "time": "2014-11-12T07:18:35.518000+00:00", "tickDelta": 0.0, "metro_open_time": 0.0}, "lastStatus": {"symptom_description": "OPERATIONAL", "symptom_category": "ON", "unit_id": "K03X03ESCALATOR", "end_time": null, "update_type": "Fix", "time": "2014-12-16T00:29:10.056000+00:00", "tickDelta": 0.0, "metro_open_time": null}, "currentBreakStatus": null, "lastFixStatus": {"symptom_description": "OPERATIONAL", "symptom_category": "ON", "unit_id": "K03X03ESCALATOR", "end_time": null, "update_type": "Fix", "time": "2014-12-16T00:29:10.056000+00:00", "tickDelta": 0.0, "metro_open_time": null}, "lastOperationalStatus": {"symptom_description": "OPERATIONAL", "symptom_category": "ON", "unit_id": "K03X03ESCALATOR", "end_time": null, "update_type": "Fix", "time": "2014-12-16T00:29:10.056000+00:00", "tickDelta": 0.0, "metro_open_time": null}, "lastBreakStatus": {"symptom_description": "Service Call", "symptom_category": "BROKEN", "unit_id": "K03X03ESCALATOR", "end_time": "2014-12-16T00:29:10.056000+00:00", "update_type": "Break", "time": "2014-12-15T23:18:08.370000+00:00", "tickDelta": 0.0, "metro_open_time": 4261.686}}, "statuses": [{"symptom_description": "OPERATIONAL", "symptom_category": "ON", "unit_id": "K03X03ESCALATOR", "end_time": null, "update_type": "Fix", "time": "2014-12-16T00:29:10.056000+00:00", "tickDelta": 0.0, "metro_open_time": null}, {"symptom_description": "Service Call", "symptom_category": "BROKEN", "unit_id": "K03X03ESCALATOR", "end_time": "2014-12-16T00:29:10.056000+00:00", "update_type": "Break", "time": "2014-12-15T23:18:08.370000+00:00", "tickDelta": 0.0, "metro_open_time": 4261.686}, {"symptom_description": "OPERATIONAL", "symptom_category": "ON", "unit_id": "K03X03ESCALATOR", "end_time": "2014-12-15T23:18:08.370000+00:00", "update_type": "Fix", "time": "2014-11-29T14:40:34.982000+00:00", "tickDelta": 0.0, "metro_open_time": 1143453.388}, {"symptom_description": "Service Call", "symptom_category": "BROKEN", "unit_id": "K03X03ESCALATOR", "end_time": "2014-11-29T14:40:34.982000+00:00", "update_type": "Break", "time": "2014-11-29T12:32:58.036000+00:00", "tickDelta": 0.0, "metro_open_time": 7656.946}, {"symptom_description": "OPERATIONAL", "symptom_category": "ON", "unit_id": "K03X03ESCALATOR", "end_time": "2014-11-29T12:32:58.036000+00:00", "update_type": "Fix", "time": "2014-11-13T22:07:40.410000+00:00", "tickDelta": 0.0, "metro_open_time": 1077917.626}, {"symptom_description": "Service Call", "symptom_category": "BROKEN", "unit_id": "K03X03ESCALATOR", "end_time": "2014-11-13T22:07:40.410000+00:00", "update_type": "Break", "time": "2014-11-13T21:32:05.649000+00:00", "tickDelta": 0.0, "metro_open_time": 2134.761}, {"symptom_description": "OPERATIONAL", "symptom_category": "ON", "unit_id": "K03X03ESCALATOR", "end_time": "2014-11-13T21:32:05.649000+00:00", "update_type": "On", "time": "2014-11-12T09:09:25.091000+00:00", "tickDelta": 0.0, "metro_open_time": 109925.649}, {"symptom_description": "Preventive Maintenance Inspection", "symptom_category": "INSPECTION", "unit_id": "K03X03ESCALATOR", "end_time": "2014-11-12T09:09:25.091000+00:00", "update_type": "Off", "time": "2014-11-12T07:18:35.518000+00:00", "tickDelta": 0.0, "metro_open_time": 0.0}, {"symptom_description": "OPERATIONAL", "symptom_category": "ON", "unit_id": "K03X03ESCALATOR", "end_time": "2014-11-12T07:18:35.518000+00:00", "update_type": "Fix", "time": "2014-11-09T20:34:49.682000+00:00", "tickDelta": 0.0, "metro_open_time": 167110.318}, {"symptom_description": "Major Repair", "symptom_category": "BROKEN", "unit_id": "K03X03ESCALATOR", "end_time": "2014-11-09T20:34:49.682000+00:00", "update_type": "Update", "time": "2014-11-07T00:27:22.367000+00:00", "tickDelta": 0.0, "metro_open_time": 198447.315}, {"symptom_description": "Service Call", "symptom_category": "BROKEN", "unit_id": "K03X03ESCALATOR", "end_time": "2014-11-07T00:27:22.367000+00:00", "update_type": "Break", "time": "2014-11-06T15:07:40.240000+00:00", "tickDelta": 0.0, "metro_open_time": 33582.127}, {"symptom_description": "OPERATIONAL", "symptom_category": "ON", "unit_id": "K03X03ESCALATOR", "end_time": "2014-11-06T15:07:40.240000+00:00", "update_type": "Fix", "time": "2014-10-15T17:55:38.149000+00:00", "tickDelta": 0.0, "metro_open_time": 1512722.091}, {"symptom_description": "Service Call", "symptom_category": "BROKEN", "unit_id": "K03X03ESCALATOR", "end_time": "2014-10-15T17:55:38.149000+00:00", "update_type": "Break", "time": "2014-10-15T17:02:53.356000+00:00", "tickDelta": 0.0, "metro_open_time": 3164.793}, {"symptom_description": "OPERATIONAL", "symptom_category": "ON", "unit_id": "K03X03ESCALATOR", "end_time": "2014-10-15T17:02:53.356000+00:00", "update_type": "On", "time": "2014-10-13T08:14:44.197000+00:00", "tickDelta": 0.0, "metro_open_time": 165773.356}, {"symptom_description": "Preventive Maintenance Inspection", "symptom_category": "INSPECTION", "unit_id": "K03X03ESCALATOR", "end_time": "2014-10-13T08:14:44.197000+00:00", "update_type": "Off", "time": "2014-10-13T05:16:12.284000+00:00", "tickDelta": 0.0, "metro_open_time": 0.0}, {"symptom_description": "OPERATIONAL", "symptom_category": "ON", "unit_id": "K03X03ESCALATOR", "end_time": "2014-10-13T05:16:12.284000+00:00", "update_type": "On", "time": "2014-09-15T07:41:53.109000+00:00", "tickDelta": 0.0, "metro_open_time": 1944000.0}, {"symptom_description": "Preventive Maintenance Inspection", "symptom_category": "INSPECTION", "unit_id": "K03X03ESCALATOR", "end_time": "2014-09-15T07:41:53.109000+00:00", "update_type": "Off", "time": "2014-09-15T04:29:20.856000+00:00", "tickDelta": 0.0, "metro_open_time": 0.0}, {"symptom_description": "OPERATIONAL", "symptom_category": "ON", "unit_id": "K03X03ESCALATOR", "end_time": "2014-09-15T04:29:20.856000+00:00", "update_type": "Fix", "time": "2014-09-01T12:13:11.769000+00:00", "tickDelta": 0.0, "metro_open_time": 960408.231}, {"symptom_description": "Service Call", "symptom_category": "BROKEN", "unit_id": "K03X03ESCALATOR", "end_time": "2014-09-01T12:13:11.769000+00:00", "update_type": "Break", "time": "2014-09-01T11:03:42.135000+00:00", "tickDelta": 0.0, "metro_open_time": 4169.634}, {"symptom_description": "OPERATIONAL", "symptom_category": "ON", "unit_id": "K03X03ESCALATOR", "end_time": "2014-09-01T11:03:42.135000+00:00", "update_type": "Fix", "time": "2014-08-31T12:29:54.554000+00:00", "tickDelta": 0.0, "metro_open_time": 63227.581000000006}, {"symptom_description": "Service Call", "symptom_category": "BROKEN", "unit_id": "K03X03ESCALATOR", "end_time": "2014-08-31T12:29:54.554000+00:00", "update_type": "Break", "time": "2014-08-31T11:04:34.290000+00:00", "tickDelta": 0.0, "metro_open_time": 5120.264}, {"symptom_description": "OPERATIONAL", "symptom_category": "ON", "unit_id": "K03X03ESCALATOR", "end_time": "2014-08-31T11:04:34.290000+00:00", "update_type": "Fix", "time": "2014-08-26T20:55:45.215000+00:00", "tickDelta": 0.0, "metro_open_time": 313729.075}, {"symptom_description": "Service Call", "symptom_category": "BROKEN", "unit_id": "K03X03ESCALATOR", "end_time": "2014-08-26T20:55:45.215000+00:00", "update_type": "Break", "time": "2014-08-26T20:14:13.352000+00:00", "tickDelta": 0.0, "metro_open_time": 2491.863}, {"symptom_description": "OPERATIONAL", "symptom_category": "ON", "unit_id": "K03X03ESCALATOR", "end_time": "2014-08-26T20:14:13.352000+00:00", "update_type": "Fix", "time": "2014-08-12T18:33:14.621000+00:00", "tickDelta": 0.0, "metro_open_time": 978058.731}, {"symptom_description": "Service Call", "symptom_category": "BROKEN", "unit_id": "K03X03ESCALATOR", "end_time": "2014-08-12T18:33:14.621000+00:00", "update_type": "Break", "time": "2014-08-12T16:28:45.384000+00:00", "tickDelta": 0.0, "metro_open_time": 7469.237}, {"symptom_description": "OPERATIONAL", "symptom_category": "ON", "unit_id": "K03X03ESCALATOR", "end_time": "2014-08-12T16:28:45.384000+00:00", "update_type": "Fix", "time": "2014-07-08T02:06:22.859000+00:00", "tickDelta": 36.102221, "metro_open_time": 2463742.525}, {"symptom_description": "CALLBACK/REPAIR", "symptom_category": "BROKEN", "unit_id": "K03X03ESCALATOR", "end_time": "2014-07-08T02:06:22.859000+00:00", "update_type": "Break", "time": "2014-07-08T01:41:26.592000+00:00", "tickDelta": 35.759524, "metro_open_time": 1496.267}, {"symptom_description": "OPERATIONAL", "symptom_category": "ON", "unit_id": "K03X03ESCALATOR", "end_time": "2014-07-08T01:41:26.592000+00:00", "update_type": "On", "time": "2014-07-01T08:08:01.484000+00:00", "tickDelta": 35.755195, "metro_open_time": 477686.592}, {"symptom_description": "PREV. MAINT. INSPECTION", "symptom_category": "INSPECTION", "unit_id": "K03X03ESCALATOR", "end_time": "2014-07-01T08:08:01.484000+00:00", "update_type": "Off", "time": "2014-07-01T07:42:37.690000+00:00", "tickDelta": 35.800421, "metro_open_time": 0.0}, {"symptom_description": "OPERATIONAL", "symptom_category": "ON", "unit_id": "K03X03ESCALATOR", "end_time": "2014-07-01T07:42:37.690000+00:00", "update_type": "On", "time": "2014-06-05T06:15:46.063000+00:00", "tickDelta": 35.829959, "metro_open_time": 1807200.0}, {"symptom_description": "PREV. MAINT. INSPECTION", "symptom_category": "INSPECTION", "unit_id": "K03X03ESCALATOR", "end_time": "2014-06-05T06:15:46.063000+00:00", "update_type": "Off", "time": "2014-06-05T05:07:21.884000+00:00", "tickDelta": 35.288542, "metro_open_time": 0.0}, {"symptom_description": "OPERATIONAL", "symptom_category": "ON", "unit_id": "K03X03ESCALATOR", "end_time": "2014-06-05T05:07:21.884000+00:00", "update_type": "On", "time": "2014-06-04T06:41:06.001000+00:00", "tickDelta": 35.73901, "metro_open_time": 68400.0}, {"symptom_description": "PREV. MAINT. INSPECTION", "symptom_category": "INSPECTION", "unit_id": "K03X03ESCALATOR", "end_time": "2014-06-04T06:41:06.001000+00:00", "update_type": "Off", "time": "2014-06-04T06:37:58.487000+00:00", "tickDelta": 35.366897, "metro_open_time": 0.0}, {"symptom_description": "OPERATIONAL", "symptom_category": "ON", "unit_id": "K03X03ESCALATOR", "end_time": "2014-06-04T06:37:58.487000+00:00", "update_type": "Fix", "time": "2014-05-25T13:46:17.864000+00:00", "tickDelta": 62.841781, "metro_open_time": 674022.1359999999}, {"symptom_description": "CALLBACK/REPAIR", "symptom_category": "BROKEN", "unit_id": "K03X03ESCALATOR", "end_time": "2014-05-25T13:46:17.864000+00:00", "update_type": "Break", "time": "2014-05-25T12:03:46.419000+00:00", "tickDelta": 35.118755, "metro_open_time": 6151.445}, {"symptom_description": "OPERATIONAL", "symptom_category": "ON", "unit_id": "K03X03ESCALATOR", "end_time": "2014-05-25T12:03:46.419000+00:00", "update_type": "Fix", "time": "2014-05-23T13:36:17.709000+00:00", "tickDelta": 35.235675, "metro_open_time": 138448.71}, {"symptom_description": "CALLBACK/REPAIR", "symptom_category": "BROKEN", "unit_id": "K03X03ESCALATOR", "end_time": "2014-05-23T13:36:17.709000+00:00", "update_type": "Break", "time": "2014-05-23T12:51:51.534000+00:00", "tickDelta": 35.171423, "metro_open_time": 2666.175}, {"symptom_description": "OPERATIONAL", "symptom_category": "ON", "unit_id": "K03X03ESCALATOR", "end_time": "2014-05-23T12:51:51.534000+00:00", "update_type": "Fix", "time": "2014-05-22T13:22:17.152000+00:00", "tickDelta": 277.195368, "metro_open_time": 66574.382}, {"symptom_description": "CALLBACK/REPAIR", "symptom_category": "BROKEN", "unit_id": "K03X03ESCALATOR", "end_time": "2014-05-22T13:22:17.152000+00:00", "update_type": "Break", "time": "2014-05-22T12:59:51.939000+00:00", "tickDelta": 1929.122425, "metro_open_time": 1345.213}, {"symptom_description": "OPERATIONAL", "symptom_category": "ON", "unit_id": "K03X03ESCALATOR", "end_time": "2014-05-22T12:59:51.939000+00:00", "update_type": "On", "time": "2014-05-22T07:40:05.725000+00:00", "tickDelta": 35.53026, "metro_open_time": 14391.939}, {"symptom_description": "PREV. MAINT. INSPECTION", "symptom_category": "INSPECTION", "unit_id": "K03X03ESCALATOR", "end_time": "2014-05-22T07:40:05.725000+00:00", "update_type": "Off", "time": "2014-05-22T04:34:59.878000+00:00", "tickDelta": 35.270382, "metro_open_time": 0.0}, {"symptom_description": "OPERATIONAL", "symptom_category": "ON", "unit_id": "K03X03ESCALATOR", "end_time": "2014-05-22T04:34:59.878000+00:00", "update_type": "Fix", "time": "2014-05-16T13:16:45.030000+00:00", "tickDelta": 34.911478, "metro_open_time": 402194.97}, {"symptom_description": "CALLBACK/REPAIR", "symptom_category": "BROKEN", "unit_id": "K03X03ESCALATOR", "end_time": "2014-05-16T13:16:45.030000+00:00", "update_type": "Break", "time": "2014-05-16T12:27:24.467000+00:00", "tickDelta": 35.161892, "metro_open_time": 2960.563}, {"symptom_description": "OPERATIONAL", "symptom_category": "ON", "unit_id": "K03X03ESCALATOR", "end_time": "2014-05-16T12:27:24.467000+00:00", "update_type": "Fix", "time": "2014-05-16T10:37:12.294000+00:00", "tickDelta": 40.42071, "metro_open_time": 6612.173}, {"symptom_description": "CALLBACK/REPAIR", "symptom_category": "BROKEN", "unit_id": "K03X03ESCALATOR", "end_time": "2014-05-16T10:37:12.294000+00:00", "update_type": "Break", "time": "2014-05-16T09:55:28.841000+00:00", "tickDelta": 40.153768, "metro_open_time": 2503.453}, {"symptom_description": "OPERATIONAL", "symptom_category": "ON", "unit_id": "K03X03ESCALATOR", "end_time": "2014-05-16T09:55:28.841000+00:00", "update_type": "Fix", "time": "2014-05-15T14:25:47.242000+00:00", "tickDelta": 35.022643, "metro_open_time": 52181.599}, {"symptom_description": "CALLBACK/REPAIR", "symptom_category": "BROKEN", "unit_id": "K03X03ESCALATOR", "end_time": "2014-05-15T14:25:47.242000+00:00", "update_type": "Break", "time": "2014-05-15T13:34:10.243000+00:00", "tickDelta": 34.882622, "metro_open_time": 3096.999}, {"symptom_description": "OPERATIONAL", "symptom_category": "ON", "unit_id": "K03X03ESCALATOR", "end_time": "2014-05-15T13:34:10.243000+00:00", "update_type": "On", "time": "2014-05-15T05:46:51.155000+00:00", "tickDelta": 35.050378, "metro_open_time": 16450.243}, {"symptom_description": "SAFETY WORK ORDER", "symptom_category": "OFF", "unit_id": "K03X03ESCALATOR", "end_time": "2014-05-15T05:46:51.155000+00:00", "update_type": "Off", "time": "2014-05-15T04:48:32.021000+00:00", "tickDelta": 35.118065, "metro_open_time": 0.0}, {"symptom_description": "OPERATIONAL", "symptom_category": "ON", "unit_id": "K03X03ESCALATOR", "end_time": "2014-05-15T04:48:32.021000+00:00", "update_type": "Fix", "time": "2014-05-07T16:44:07.336000+00:00", "tickDelta": 34.98033, "metro_open_time": 526552.664}, {"symptom_description": "CALLBACK/REPAIR", "symptom_category": "BROKEN", "unit_id": "K03X03ESCALATOR", "end_time": "2014-05-07T16:44:07.336000+00:00", "update_type": "Break", "time": "2014-05-07T15:54:35.010000+00:00", "tickDelta": 34.728894, "metro_open_time": 2972.326}, {"symptom_description": "OPERATIONAL", "symptom_category": "ON", "unit_id": "K03X03ESCALATOR", "end_time": "2014-05-07T15:54:35.010000+00:00", "update_type": "Fix", "time": "2014-05-04T14:42:47.249000+00:00", "tickDelta": 35.47765, "metro_open_time": 209507.761}, {"symptom_description": "CALLBACK/REPAIR", "symptom_category": "BROKEN", "unit_id": "K03X03ESCALATOR", "end_time": "2014-05-04T14:42:47.249000+00:00", "update_type": "Break", "time": "2014-05-04T13:57:58.994000+00:00", "tickDelta": 34.711412, "metro_open_time": 2688.255}, {"symptom_description": "OPERATIONAL", "symptom_category": "ON", "unit_id": "K03X03ESCALATOR", "end_time": "2014-05-04T13:57:58.994000+00:00", "update_type": "On", "time": "2014-04-18T09:06:27.029000+00:00", "tickDelta": 35.240001, "metro_open_time": 1133491.965}, {"symptom_description": "PREV. MAINT. INSPECTION", "symptom_category": "INSPECTION", "unit_id": "K03X03ESCALATOR", "end_time": "2014-04-18T09:06:27.029000+00:00", "update_type": "Off", "time": "2014-04-18T06:04:30.249000+00:00", "tickDelta": 35.135528, "metro_open_time": 387.029}, {"symptom_description": "OPERATIONAL", "symptom_category": "ON", "unit_id": "K03X03ESCALATOR", "end_time": "2014-04-18T06:04:30.249000+00:00", "update_type": "Fix", "time": "2014-04-16T08:36:20.042000+00:00", "tickDelta": 35.05229, "metro_open_time": 136800.0}, {"symptom_description": "CALLBACK/REPAIR", "symptom_category": "BROKEN", "unit_id": "K03X03ESCALATOR", "end_time": "2014-04-16T08:36:20.042000+00:00", "update_type": "Break", "time": "2014-04-15T18:23:10.338000+00:00", "tickDelta": 35.591843, "metro_open_time": 34609.662}, {"symptom_description": "OPERATIONAL", "symptom_category": "ON", "unit_id": "K03X03ESCALATOR", "end_time": "2014-04-15T18:23:10.338000+00:00", "update_type": "Fix", "time": "2014-04-13T20:10:59.496000+00:00", "tickDelta": 34.789799, "metro_open_time": 130330.842}, {"symptom_description": "CALLBACK/REPAIR", "symptom_category": "BROKEN", "unit_id": "K03X03ESCALATOR", "end_time": "2014-04-13T20:10:59.496000+00:00", "update_type": "Break", "time": "2014-04-13T19:13:41.939000+00:00", "tickDelta": 34.688495, "metro_open_time": 3437.557}, {"symptom_description": "OPERATIONAL", "symptom_category": "ON", "unit_id": "K03X03ESCALATOR", "end_time": "2014-04-13T19:13:41.939000+00:00", "update_type": "Fix", "time": "2014-04-13T13:08:41.043000+00:00", "tickDelta": 34.620845, "metro_open_time": 21900.896}, {"symptom_description": "CALLBACK/REPAIR", "symptom_category": "BROKEN", "unit_id": "K03X03ESCALATOR", "end_time": "2014-04-13T13:08:41.043000+00:00", "update_type": "Break", "time": "2014-04-13T11:54:09.003000+00:00", "tickDelta": 36.03546, "metro_open_time": 4472.04}, {"symptom_description": "OPERATIONAL", "symptom_category": "ON", "unit_id": "K03X03ESCALATOR", "end_time": "2014-04-13T11:54:09.003000+00:00", "update_type": "On", "time": "2014-03-22T09:11:34.107000+00:00", "tickDelta": 34.685847, "metro_open_time": 1533249.003}, {"symptom_description": "PREV. MAINT. INSPECTION", "symptom_category": "INSPECTION", "unit_id": "K03X03ESCALATOR", "end_time": "2014-03-22T09:11:34.107000+00:00", "update_type": "Off", "time": "2014-03-22T06:19:32.144000+00:00", "tickDelta": 34.610865, "metro_open_time": 2427.856}, {"symptom_description": "OPERATIONAL", "symptom_category": "ON", "unit_id": "K03X03ESCALATOR", "end_time": "2014-03-22T06:19:32.144000+00:00", "update_type": "Fix", "time": "2014-03-20T20:51:12.239000+00:00", "tickDelta": 34.991699, "metro_open_time": 102499.905}, {"symptom_description": "CALLBACK/REPAIR", "symptom_category": "BROKEN", "unit_id": "K03X03ESCALATOR", "end_time": "2014-03-20T20:51:12.239000+00:00", "update_type": "Break", "time": "2014-03-20T19:42:07.933000+00:00", "tickDelta": 34.272019, "metro_open_time": 4144.306}, {"symptom_description": "OPERATIONAL", "symptom_category": "ON", "unit_id": "K03X03ESCALATOR", "end_time": "2014-03-20T19:42:07.933000+00:00", "update_type": "On", "time": "2014-02-26T09:13:30.224000+00:00", "tickDelta": 36.117947, "metro_open_time": 1564927.933}, {"symptom_description": "PREV. MAINT. INSPECTION", "symptom_category": "INSPECTION", "unit_id": "K03X03ESCALATOR", "end_time": "2014-02-26T09:13:30.224000+00:00", "update_type": "Off", "time": "2014-02-26T05:24:49.402000+00:00", "tickDelta": 36.1344, "metro_open_time": 0.0}, {"symptom_description": "OPERATIONAL", "symptom_category": "ON", "unit_id": "K03X03ESCALATOR", "end_time": "2014-02-26T05:24:49.402000+00:00", "update_type": "Fix", "time": "2014-02-08T13:36:08.812000+00:00", "tickDelta": 53.654306, "metro_open_time": 1236231.188}, {"symptom_description": "CALLBACK/REPAIR", "symptom_category": "BROKEN", "unit_id": "K03X03ESCALATOR", "end_time": "2014-02-08T13:36:08.812000+00:00", "update_type": "Break", "time": "2014-02-08T12:49:23.474000+00:00", "tickDelta": 49.757709, "metro_open_time": 2805.338}, {"symptom_description": "OPERATIONAL", "symptom_category": "ON", "unit_id": "K03X03ESCALATOR", "end_time": "2014-02-08T12:49:23.474000+00:00", "update_type": "Fix", "time": "2014-01-29T14:56:29.599000+00:00", "tickDelta": 48.3653, "metro_open_time": 687173.875}, {"symptom_description": "CALLBACK/REPAIR", "symptom_category": "BROKEN", "unit_id": "K03X03ESCALATOR", "end_time": "2014-01-29T14:56:29.599000+00:00", "update_type": "Break", "time": "2014-01-29T13:48:41.323000+00:00", "tickDelta": 51.549678, "metro_open_time": 4068.276}, {"symptom_description": "OPERATIONAL", "symptom_category": "ON", "unit_id": "K03X03ESCALATOR", "end_time": "2014-01-29T13:48:41.323000+00:00", "update_type": "On", "time": "2014-01-15T09:29:08.340000+00:00", "tickDelta": 50.29059, "metro_open_time": 985721.323}, {"symptom_description": "PREV. MAINT. INSPECTION", "symptom_category": "INSPECTION", "unit_id": "K03X03ESCALATOR", "end_time": "2014-01-15T09:29:08.340000+00:00", "update_type": "Off", "time": "2014-01-15T05:57:41.119000+00:00", "tickDelta": 73.629459, "metro_open_time": 0.0}, {"symptom_description": "OPERATIONAL", "symptom_category": "ON", "unit_id": "K03X03ESCALATOR", "end_time": "2014-01-15T05:57:41.119000+00:00", "update_type": "On", "time": "2013-12-07T08:33:57.220000+00:00", "tickDelta": 33.359996, "metro_open_time": 2700000.0}, {"symptom_description": "PREV. MAINT. INSPECTION", "symptom_category": "INSPECTION", "unit_id": "K03X03ESCALATOR", "end_time": "2013-12-07T08:33:57.220000+00:00", "update_type": "Off", "time": "2013-12-07T05:04:47.883000+00:00", "tickDelta": 36.064068, "metro_open_time": 10512.117}, {"symptom_description": "OPERATIONAL", "symptom_category": "ON", "unit_id": "K03X03ESCALATOR", "end_time": "2013-12-07T05:04:47.883000+00:00", "update_type": "On", "time": "2013-12-06T10:10:17.980000+00:00", "tickDelta": 33.282131, "metro_open_time": 68069.903}, {"symptom_description": "PREV. MAINT. INSPECTION", "symptom_category": "INSPECTION", "unit_id": "K03X03ESCALATOR", "end_time": "2013-12-06T10:10:17.980000+00:00", "update_type": "Off", "time": "2013-12-06T08:06:49.384000+00:00", "tickDelta": 34.57913, "metro_open_time": 617.98}, {"symptom_description": "OPERATIONAL", "symptom_category": "ON", "unit_id": "K03X03ESCALATOR", "end_time": "2013-12-06T08:06:49.384000+00:00", "update_type": "Fix", "time": "2013-11-26T04:47:05.231000+00:00", "tickDelta": 73.284134, "metro_open_time": 691974.769}, {"symptom_description": "CALLBACK/REPAIR", "symptom_category": "BROKEN", "unit_id": "K03X03ESCALATOR", "end_time": "2013-11-26T04:47:05.231000+00:00", "update_type": "Break", "time": "2013-11-26T03:52:11.029000+00:00", "tickDelta": 44.795713, "metro_open_time": 3294.202}, {"symptom_description": "OPERATIONAL", "symptom_category": "ON", "unit_id": "K03X03ESCALATOR", "end_time": "2013-11-26T03:52:11.029000+00:00", "update_type": "On", "time": "2013-11-21T08:06:37.240000+00:00", "tickDelta": 88.301819, "metro_open_time": 345131.029}, {"symptom_description": "PREV. MAINT. INSPECTION", "symptom_category": "INSPECTION", "unit_id": "K03X03ESCALATOR", "end_time": "2013-11-21T08:06:37.240000+00:00", "update_type": "Off", "time": "2013-11-21T05:15:53.224000+00:00", "tickDelta": 65.16131, "metro_open_time": 0.0}, {"symptom_description": "OPERATIONAL", "symptom_category": "ON", "unit_id": "K03X03ESCALATOR", "end_time": "2013-11-21T05:15:53.224000+00:00", "update_type": "Fix", "time": "2013-11-15T00:01:28.412000+00:00", "tickDelta": 102.283056, "metro_open_time": 435511.588}, {"symptom_description": "CALLBACK/REPAIR", "symptom_category": "BROKEN", "unit_id": "K03X03ESCALATOR", "end_time": "2013-11-15T00:01:28.412000+00:00", "update_type": "Break", "time": "2013-11-14T23:03:40.472000+00:00", "tickDelta": 73.015453, "metro_open_time": 3467.94}, {"symptom_description": "OPERATIONAL", "symptom_category": "ON", "unit_id": "K03X03ESCALATOR", "end_time": "2013-11-14T23:03:40.472000+00:00", "update_type": "Fix", "time": "2013-11-10T16:45:01.411000+00:00", "tickDelta": 35.022179, "metro_open_time": 296319.061}, {"symptom_description": "CALLBACK/REPAIR", "symptom_category": "BROKEN", "unit_id": "K03X03ESCALATOR", "end_time": "2013-11-10T16:45:01.411000+00:00", "update_type": "Break", "time": "2013-11-10T12:49:50.751000+00:00", "tickDelta": 33.832713, "metro_open_time": 14110.66}, {"symptom_description": "OPERATIONAL", "symptom_category": "ON", "unit_id": "K03X03ESCALATOR", "end_time": "2013-11-10T12:49:50.751000+00:00", "update_type": "Fix", "time": "2013-11-02T12:51:57.604000+00:00", "tickDelta": 67.48718, "metro_open_time": 554273.147}, {"symptom_description": "CALLBACK/REPAIR", "symptom_category": "BROKEN", "unit_id": "K03X03ESCALATOR", "end_time": "2013-11-02T12:51:57.604000+00:00", "update_type": "Break", "time": "2013-11-02T12:50:50.117000+00:00", "tickDelta": 60.276517, "metro_open_time": 67.487}, {"symptom_description": "OPERATIONAL", "symptom_category": "ON", "unit_id": "K03X03ESCALATOR", "end_time": "2013-11-02T12:50:50.117000+00:00", "update_type": "Fix", "time": "2013-10-26T17:11:07.014000+00:00", "tickDelta": 42.667823, "metro_open_time": 470383.103}, {"symptom_description": "CALLBACK/REPAIR", "symptom_category": "BROKEN", "unit_id": "K03X03ESCALATOR", "end_time": "2013-10-26T17:11:07.014000+00:00", "update_type": "Break", "time": "2013-10-26T15:17:07.715000+00:00", "tickDelta": 41.923675, "metro_open_time": 6839.299}, {"symptom_description": "OPERATIONAL", "symptom_category": "ON", "unit_id": "K03X03ESCALATOR", "end_time": "2013-10-26T15:17:07.715000+00:00", "update_type": "On", "time": "2013-10-22T18:53:28.307000+00:00", "tickDelta": 40.780864, "metro_open_time": 264219.408}, {"symptom_description": "SAFETY INSPECTION", "symptom_category": "INSPECTION", "unit_id": "K03X03ESCALATOR", "end_time": "2013-10-22T18:53:28.307000+00:00", "update_type": "Off", "time": "2013-10-22T11:57:15.804000+00:00", "tickDelta": 42.37643, "metro_open_time": 24972.503}, {"symptom_description": "OPERATIONAL", "symptom_category": "ON", "unit_id": "K03X03ESCALATOR", "end_time": "2013-10-22T11:57:15.804000+00:00", "update_type": "Fix", "time": "2013-10-10T16:18:38.338000+00:00", "tickDelta": 36.643064, "metro_open_time": 819517.466}, {"symptom_description": "CALLBACK/REPAIR", "symptom_category": "BROKEN", "unit_id": "K03X03ESCALATOR", "end_time": "2013-10-10T16:18:38.338000+00:00", "update_type": "Break", "time": "2013-10-10T15:23:15.956000+00:00", "tickDelta": 31.918094, "metro_open_time": 3322.382}, {"symptom_description": "OPERATIONAL", "symptom_category": "ON", "unit_id": "K03X03ESCALATOR", "end_time": "2013-10-10T15:23:15.956000+00:00", "update_type": "Fix", "time": "2013-10-08T15:13:46.918000+00:00", "tickDelta": 34.041686, "metro_open_time": 137369.038}, {"symptom_description": "CALLBACK/REPAIR", "symptom_category": "BROKEN", "unit_id": "K03X03ESCALATOR", "end_time": "2013-10-08T15:13:46.918000+00:00", "update_type": "Break", "time": "2013-10-08T12:05:45.337000+00:00", "tickDelta": 44.482676, "metro_open_time": 11281.581}, {"symptom_description": "OPERATIONAL", "symptom_category": "ON", "unit_id": "K03X03ESCALATOR", "end_time": "2013-10-08T12:05:45.337000+00:00", "update_type": "Fix", "time": "2013-10-07T10:34:22.175000+00:00", "tickDelta": 31.894118, "metro_open_time": 73883.162}, {"symptom_description": "CALLBACK/REPAIR", "symptom_category": "BROKEN", "unit_id": "K03X03ESCALATOR", "end_time": "2013-10-07T10:34:22.175000+00:00", "update_type": "Break", "time": "2013-10-07T09:20:59.372000+00:00", "tickDelta": 49.455408, "metro_open_time": 4402.803}, {"symptom_description": "OPERATIONAL", "symptom_category": "ON", "unit_id": "K03X03ESCALATOR", "end_time": "2013-10-07T09:20:59.372000+00:00", "update_type": "On", "time": "2013-10-05T08:31:34.612000+00:00", "tickDelta": 34.218608, "metro_open_time": 134459.372}, {"symptom_description": "PREV. MAINT. INSPECTION", "symptom_category": "INSPECTION", "unit_id": "K03X03ESCALATOR", "end_time": "2013-10-05T08:31:34.612000+00:00", "update_type": "Off", "time": "2013-10-05T04:42:02.531000+00:00", "tickDelta": 33.888774, "metro_open_time": 8277.469}, {"symptom_description": "OPERATIONAL", "symptom_category": "ON", "unit_id": "K03X03ESCALATOR", "end_time": "2013-10-05T04:42:02.531000+00:00", "update_type": "Fix", "time": "2013-10-03T01:08:51.225000+00:00", "tickDelta": 32.858401, "metro_open_time": 149591.30599999998}, {"symptom_description": "CALLBACK/REPAIR", "symptom_category": "BROKEN", "unit_id": "K03X03ESCALATOR", "end_time": "2013-10-03T01:08:51.225000+00:00", "update_type": "Break", "time": "2013-10-02T23:46:48.245000+00:00", "tickDelta": 32.948568, "metro_open_time": 4922.98}, {"symptom_description": "OPERATIONAL", "symptom_category": "ON", "unit_id": "K03X03ESCALATOR", "end_time": "2013-10-02T23:46:48.245000+00:00", "update_type": "Fix", "time": "2013-10-02T18:16:36.114000+00:00", "tickDelta": 32.426445, "metro_open_time": 19812.131}, {"symptom_description": "CALLBACK/REPAIR", "symptom_category": "BROKEN", "unit_id": "K03X03ESCALATOR", "end_time": "2013-10-02T18:16:36.114000+00:00", "update_type": "Break", "time": "2013-10-02T15:24:24.874000+00:00", "tickDelta": 32.274471, "metro_open_time": 10331.24}, {"symptom_description": "OPERATIONAL", "symptom_category": "ON", "unit_id": "K03X03ESCALATOR", "end_time": "2013-10-02T15:24:24.874000+00:00", "update_type": "Fix", "time": "2013-10-02T13:28:13.160000+00:00", "tickDelta": 32.92134, "metro_open_time": 6971.714}, {"symptom_description": "CALLBACK/REPAIR", "symptom_category": "BROKEN", "unit_id": "K03X03ESCALATOR", "end_time": "2013-10-02T13:28:13.160000+00:00", "update_type": "Break", "time": "2013-10-02T11:49:41.414000+00:00", "tickDelta": 33.547452, "metro_open_time": 5911.746}, {"symptom_description": "OPERATIONAL", "symptom_category": "ON", "unit_id": "K03X03ESCALATOR", "end_time": "2013-10-02T11:49:41.414000+00:00", "update_type": "On", "time": "2013-09-21T06:42:27.307000+00:00", "tickDelta": 32.7565, "metro_open_time": 767234.107}, {"symptom_description": "PREV. MAINT. INSPECTION", "symptom_category": "INSPECTION", "unit_id": "K03X03ESCALATOR", "end_time": "2013-09-21T06:42:27.307000+00:00", "update_type": "Off", "time": "2013-09-21T05:49:58.309000+00:00", "tickDelta": 32.958359, "metro_open_time": 3148.998}, {"symptom_description": "OPERATIONAL", "symptom_category": "ON", "unit_id": "K03X03ESCALATOR", "end_time": "2013-09-21T05:49:58.309000+00:00", "update_type": "On", "time": "2013-09-10T08:52:45.089000+00:00", "tickDelta": 31.051726, "metro_open_time": 766198.309}, {"symptom_description": "PREV. MAINT. INSPECTION", "symptom_category": "INSPECTION", "unit_id": "K03X03ESCALATOR", "end_time": "2013-09-10T08:52:45.089000+00:00", "update_type": "Off", "time": "2013-09-10T07:28:21.399000+00:00", "tickDelta": 36.645237, "metro_open_time": 0.0}, {"symptom_description": "OPERATIONAL", "symptom_category": "ON", "unit_id": "K03X03ESCALATOR", "end_time": "2013-09-10T07:28:21.399000+00:00", "update_type": "On", "time": "2013-08-29T09:17:50.799000+00:00", "tickDelta": 36.92192, "metro_open_time": 834129.201}, {"symptom_description": "PREV. MAINT. INSPECTION", "symptom_category": "INSPECTION", "unit_id": "K03X03ESCALATOR", "end_time": "2013-08-29T09:17:50.799000+00:00", "update_type": "Off", "time": "2013-08-29T04:37:24.201000+00:00", "tickDelta": 38.468917, "metro_open_time": 1070.799}, {"symptom_description": "OPERATIONAL", "symptom_category": "ON", "unit_id": "K03X03ESCALATOR", "end_time": "2013-08-29T04:37:24.201000+00:00", "update_type": "On", "time": "2013-08-01T09:41:20.342000+00:00", "tickDelta": 48.123616, "metro_open_time": 1941519.658}, {"symptom_description": "PREV. MAINT. INSPECTION", "symptom_category": "INSPECTION", "unit_id": "K03X03ESCALATOR", "end_time": "2013-08-01T09:41:20.342000+00:00", "update_type": "Off", "time": "2013-08-01T05:05:53.038000+00:00", "tickDelta": 40.717736, "metro_open_time": 2480.342}, {"symptom_description": "OPERATIONAL", "symptom_category": "ON", "unit_id": "K03X03ESCALATOR", "end_time": "2013-08-01T05:05:53.038000+00:00", "update_type": "On", "time": "2013-07-24T08:31:53.724000+00:00", "tickDelta": 43.481016, "metro_open_time": 554400.0}, {"symptom_description": "PREV. MAINT. INSPECTION", "symptom_category": "INSPECTION", "unit_id": "K03X03ESCALATOR", "end_time": "2013-07-24T08:31:53.724000+00:00", "update_type": "Off", "time": "2013-07-24T04:40:51.517000+00:00", "tickDelta": 38.756635, "metro_open_time": 0.0}, {"symptom_description": "OPERATIONAL", "symptom_category": "ON", "unit_id": "K03X03ESCALATOR", "end_time": "2013-07-24T04:40:51.517000+00:00", "update_type": "Fix", "time": "2013-07-15T21:11:55.266000+00:00", "tickDelta": 58.840161, "metro_open_time": 578884.7339999999}, {"symptom_description": "POWER SURGE/OUTAGE", "symptom_category": "BROKEN", "unit_id": "K03X03ESCALATOR", "end_time": "2013-07-15T21:11:55.266000+00:00", "update_type": "Break", "time": "2013-07-15T20:11:08.748000+00:00", "tickDelta": 52.916272, "metro_open_time": 3646.518}, {"symptom_description": "OPERATIONAL", "symptom_category": "ON", "unit_id": "K03X03ESCALATOR", "end_time": "2013-07-15T20:11:08.748000+00:00", "update_type": "Fix", "time": "2013-07-13T02:43:44.660000+00:00", "tickDelta": 44.642266, "metro_open_time": 188844.088}, {"symptom_description": "CALLBACK/REPAIR", "symptom_category": "BROKEN", "unit_id": "K03X03ESCALATOR", "end_time": "2013-07-13T02:43:44.660000+00:00", "update_type": "Break", "time": "2013-07-13T02:15:04.493000+00:00", "tickDelta": 37.088348, "metro_open_time": 1720.167}, {"symptom_description": "OPERATIONAL", "symptom_category": "ON", "unit_id": "K03X03ESCALATOR", "end_time": "2013-07-13T02:15:04.493000+00:00", "update_type": "Fix", "time": "2013-06-28T21:09:11.056000+00:00", "tickDelta": 39.355963, "metro_open_time": 990353.437}, {"symptom_description": "CALLBACK/REPAIR", "symptom_category": "BROKEN", "unit_id": "K03X03ESCALATOR", "end_time": "2013-06-28T21:09:11.056000+00:00", "update_type": "Break", "time": "2013-06-28T19:37:09.823000+00:00", "tickDelta": 43.811564, "metro_open_time": 5521.233}, {"symptom_description": "OPERATIONAL", "symptom_category": "ON", "unit_id": "K03X03ESCALATOR", "end_time": "2013-06-28T19:37:09.823000+00:00", "update_type": "Fix", "time": "2013-06-28T02:27:02.510000+00:00", "tickDelta": 37.206233, "metro_open_time": 43807.312999999995}, {"symptom_description": "CALLBACK/REPAIR", "symptom_category": "BROKEN", "unit_id": "K03X03ESCALATOR", "end_time": "2013-06-28T02:27:02.510000+00:00", "update_type": "Break", "time": "2013-06-28T01:32:27.990000+00:00", "tickDelta": 41.481639, "metro_open_time": 3274.52}, {"symptom_description": "OPERATIONAL", "symptom_category": "ON", "unit_id": "K03X03ESCALATOR", "end_time": "2013-06-28T01:32:27.990000+00:00", "update_type": "Fix", "time": "2013-06-27T10:32:35.504000+00:00", "tickDelta": 59.883596, "metro_open_time": 53992.486}, {"symptom_description": "CALLBACK/REPAIR", "symptom_category": "BROKEN", "unit_id": "K03X03ESCALATOR", "end_time": "2013-06-27T10:32:35.504000+00:00", "update_type": "Break", "time": "2013-06-27T09:29:41.517000+00:00", "tickDelta": 95.293374, "metro_open_time": 3773.987}, {"symptom_description": "OPERATIONAL", "symptom_category": "ON", "unit_id": "K03X03ESCALATOR", "end_time": "2013-06-27T09:29:41.517000+00:00", "update_type": "On", "time": "2013-06-18T09:58:46.805000+00:00", "tickDelta": 43.08704, "metro_open_time": 621054.712}, {"symptom_description": "PREV. MAINT. INSPECTION", "symptom_category": "INSPECTION", "unit_id": "K03X03ESCALATOR", "end_time": "2013-06-18T09:58:46.805000+00:00", "update_type": "Off", "time": "2013-06-18T05:30:33.361000+00:00", "tickDelta": 41.207006, "metro_open_time": 3526.805}, {"symptom_description": "OPERATIONAL", "symptom_category": "ON", "unit_id": "K03X03ESCALATOR", "end_time": "2013-06-18T05:30:33.361000+00:00", "update_type": "Fix", "time": "2013-06-15T06:34:42.300000+00:00", "tickDelta": 31.074449, "metro_open_time": 203117.7}, {"symptom_description": "CALLBACK/REPAIR", "symptom_category": "BROKEN", "unit_id": "K03X03ESCALATOR", "end_time": "2013-06-15T06:34:42.300000+00:00", "update_type": "Break", "time": "2013-06-15T05:19:11.990000+00:00", "tickDelta": 34.886786, "metro_open_time": 4530.31}, {"symptom_description": "OPERATIONAL", "symptom_category": "ON", "unit_id": "K03X03ESCALATOR", "end_time": "2013-06-15T05:19:11.990000+00:00", "update_type": "Fix", "time": "2013-06-13T22:01:34.456000+00:00", "tickDelta": 3239.695087, "metro_open_time": 94657.53400000001}, {"symptom_description": "POWER SURGE/OUTAGE", "symptom_category": "BROKEN", "unit_id": "K03X03ESCALATOR", "end_time": "2013-06-13T22:01:34.456000+00:00", "update_type": "Break", "time": "2013-06-13T19:01:25.331000+00:00", "tickDelta": 3234.153981, "metro_open_time": 10809.125}, {"symptom_description": "OPERATIONAL", "symptom_category": "ON", "unit_id": "K03X03ESCALATOR", "end_time": "2013-06-13T19:01:25.331000+00:00", "update_type": "Fix", "time": "2013-06-07T10:46:32.136000+00:00", "tickDelta": 32.004149, "metro_open_time": 447293.195}, {"symptom_description": "CALLBACK/REPAIR", "symptom_category": "BROKEN", "unit_id": "K03X03ESCALATOR", "end_time": "2013-06-07T10:46:32.136000+00:00", "update_type": "Break", "time": "2013-06-07T09:46:38.418000+00:00", "tickDelta": 21.953375, "metro_open_time": 3593.718}, {"symptom_description": "OPERATIONAL", "symptom_category": "ON", "unit_id": "K03X03ESCALATOR", "end_time": "2013-06-07T09:46:38.418000+00:00", "update_type": "Update", "time": "2013-06-01T16:38:21.475000+00:00", "tickDelta": 0.0, "metro_open_time": 389296.94299999997}]}